odoo/addons/odoo_2_odoo_sale_no_picking/README.rst
odoo/addons/odoo_2_odoo_sale_no_picking/__init__.py
odoo/addons/odoo_2_odoo_sale_no_picking/__manifest__.py
odoo/addons/odoo_2_odoo_sale_no_picking/demo/odoo.data.transfer.template.csv
odoo/addons/odoo_2_odoo_sale_no_picking/demo/odoo.data.transfer.template.line.csv
odoo/addons/odoo_2_odoo_sale_no_picking/readme/CONTRIBUTORS.md
odoo/addons/odoo_2_odoo_sale_no_picking/readme/DESCRIPTION.md
odoo/addons/odoo_2_odoo_sale_no_picking/readme/USAGE.md
odoo/addons/odoo_2_odoo_sale_no_picking/static/description/icon.png
odoo/addons/odoo_2_odoo_sale_no_picking/static/description/index.html
odoo/addons/odoo_2_odoo_sale_no_picking/tests/__init__.py
odoo/addons/odoo_2_odoo_sale_no_picking/tests/test_odoo_2_odoo_sale_no_picking.py
odoo/addons/odoo_2_odoo_sale_no_picking/wizard/__init__.py
odoo/addons/odoo_2_odoo_sale_no_picking/wizard/odoo_data_transfer_wizard.py
odoo_addon_odoo_2_odoo_sale_no_picking-16.0.1.0.0.1.dist-info/METADATA
odoo_addon_odoo_2_odoo_sale_no_picking-16.0.1.0.0.1.dist-info/WHEEL
odoo_addon_odoo_2_odoo_sale_no_picking-16.0.1.0.0.1.dist-info/top_level.txt
odoo_addon_odoo_2_odoo_sale_no_picking-16.0.1.0.0.1.dist-info/RECORD
