Metadata-Version: 2.1
Name: odoo-addon-odoo_2_odoo_sale_no_picking
Version: 16.0.1.0.0.1
Summary: Avoid picking creation from sale orders created using Odoo 2 Odoo Data Transfer
Home-page: https://github.com/sygel-technology/sy-sale-workflow
Author: Sygel
License: AGPL-3
Classifier: Programming Language :: Python
Classifier: Framework :: Odoo
Classifier: Framework :: Odoo :: 16.0
Classifier: License :: OSI Approved :: GNU Affero General Public License v3
Requires-Python: >=3.10
Requires-Dist: odoo-addon-odoo-2-odoo-data-transfer<16.1dev,>=16.0dev
Requires-Dist: odoo<16.1dev,>=16.0a
